CONTRIBUTORS.rst
LICENSE.rst
MANIFEST.in
README.rst
setup.py
py3kwarn/__init__.py
py3kwarn/__init__.pyc
py3kwarn/__main__.py
py3kwarn/main.py
py3kwarn/main.pyc
py3kwarn/tests.py
py3kwarn/tests.pyc
py3kwarn.egg-info/PKG-INFO
py3kwarn.egg-info/SOURCES.txt
py3kwarn.egg-info/dependency_links.txt
py3kwarn.egg-info/entry_points.txt
py3kwarn.egg-info/not-zip-safe
py3kwarn.egg-info/top_level.txt
py3kwarn/__pycache__/__init__.cpython-33.pyc
py3kwarn/__pycache__/__main__.cpython-33.pyc
py3kwarn/__pycache__/main.cpython-33.pyc
py3kwarn/__pycache__/tests.cpython-33.pyc
py3kwarn2to3/Grammar.txt
py3kwarn2to3/PatternGrammar.txt
py3kwarn2to3/__init__.py
py3kwarn2to3/__main__.py
py3kwarn2to3/btm_matcher.py
py3kwarn2to3/btm_utils.py
py3kwarn2to3/fixer_base.py
py3kwarn2to3/fixer_util.py
py3kwarn2to3/main.py
py3kwarn2to3/patcomp.py
py3kwarn2to3/pygram.py
py3kwarn2to3/pytree.py
py3kwarn2to3/refactor.py
py3kwarn2to3/fixes/__init__.py
py3kwarn2to3/fixes/fix_apply.py
py3kwarn2to3/fixes/fix_basestring.py
py3kwarn2to3/fixes/fix_buffer.py
py3kwarn2to3/fixes/fix_callable.py
py3kwarn2to3/fixes/fix_dict.py
py3kwarn2to3/fixes/fix_except.py
py3kwarn2to3/fixes/fix_exec.py
py3kwarn2to3/fixes/fix_execfile.py
py3kwarn2to3/fixes/fix_exitfunc.py
py3kwarn2to3/fixes/fix_filter.py
py3kwarn2to3/fixes/fix_funcattrs.py
py3kwarn2to3/fixes/fix_getcwdu.py
py3kwarn2to3/fixes/fix_has_key.py
py3kwarn2to3/fixes/fix_idioms.py
py3kwarn2to3/fixes/fix_import.py
py3kwarn2to3/fixes/fix_imports.py
py3kwarn2to3/fixes/fix_imports2.py
py3kwarn2to3/fixes/fix_input.py
py3kwarn2to3/fixes/fix_intern.py
py3kwarn2to3/fixes/fix_isinstance.py
py3kwarn2to3/fixes/fix_itertools.py
py3kwarn2to3/fixes/fix_itertools_imports.py
py3kwarn2to3/fixes/fix_long.py
py3kwarn2to3/fixes/fix_map.py
py3kwarn2to3/fixes/fix_metaclass.py
py3kwarn2to3/fixes/fix_methodattrs.py
py3kwarn2to3/fixes/fix_ne.py
py3kwarn2to3/fixes/fix_next.py
py3kwarn2to3/fixes/fix_nonzero.py
py3kwarn2to3/fixes/fix_numliterals.py
py3kwarn2to3/fixes/fix_operator.py
py3kwarn2to3/fixes/fix_paren.py
py3kwarn2to3/fixes/fix_print.py
py3kwarn2to3/fixes/fix_raise.py
py3kwarn2to3/fixes/fix_raw_input.py
py3kwarn2to3/fixes/fix_reduce.py
py3kwarn2to3/fixes/fix_renames.py
