Metadata-Version: 1.1
Name: py3kwarn
Version: 0.4.4
Summary: Detects code that is not Python 3 compatible.
Home-page: https://github.com/liamcurry/py3kwarn
Author: Liam Curry
Author-email: liam@curry.name
License: MIT
Platform: UNKNOWN
Classifier: Environment :: Console
Classifier: Intended Audience :: Developers
Classifier: License :: OSI Approved :: MIT License
Classifier: Programming Language :: Python
Classifier: Programming Language :: Python :: 2
Classifier: Programming Language :: Python :: 2.6
Classifier: Programming Language :: Python :: 2.7
Classifier: Programming Language :: Python :: 3
Classifier: Programming Language :: Python :: 3.3
Classifier: Topic :: Software Development
Classifier: Topic :: Utilities
